sdc_cryptography-1.2.1-py3.9-nspkg.pth
sdc/crypto/__init__.py
sdc/crypto/decrypter.py
sdc/crypto/encrypter.py
sdc/crypto/exceptions.py
sdc/crypto/helper.py
sdc/crypto/jwe_helper.py
sdc/crypto/jwt_helper.py
sdc/crypto/key_store.py
sdc/crypto/scripts/__init__.py
sdc/crypto/scripts/generate_keys.py
sdc_cryptography-1.2.1.data/scripts/generate_keys.py
sdc_cryptography-1.2.1.dist-info/LICENSE
sdc_cryptography-1.2.1.dist-info/METADATA
sdc_cryptography-1.2.1.dist-info/WHEEL
sdc_cryptography-1.2.1.dist-info/namespace_packages.txt
sdc_cryptography-1.2.1.dist-info/top_level.txt
sdc_cryptography-1.2.1.dist-info/RECORD
