Metadata-Version: 2.1
Name: sdc-cryptography
Version: 1.2.1
Summary: A shared library for SDC services that use JWT with JWE
Home-page: https://github.com/ONSdigital/sdc-cryptography
Author: ONS
Classifier: Operating System :: OS Independent
Classifier: Programming Language :: Python :: 3.12
Classifier: Programming Language :: Python :: 3.11
Classifier: Programming Language :: Python :: 3.10
Classifier: Programming Language :: Python :: 3.9
Classifier: License :: OSI Approved :: MIT License
License-File: LICENSE
Requires-Dist: jwcrypto
Requires-Dist: cryptography
Requires-Dist: PyYAML
